LICENSE
MANIFEST.in
README.rst
setup.py
testall.py
docs/Makefile
docs/architecture.rst
docs/conf.py
docs/create_plugin.rst
docs/event_index.rst
docs/features.rst
docs/glossary.rst
docs/guide_xep_0030.rst
docs/handlersmatchers.rst
docs/index.rst
docs/license.rst
docs/make.bat
docs/plugin_arch.rst
docs/sasl.rst
docs/xeps.rst
docs/xmpp_tdg.rst
docs/_static/agogo.css
docs/_static/basic.css
docs/_static/default.css
docs/_static/haiku.css
docs/_static/header.png
docs/_static/ir_black.css
docs/_static/nature.css
docs/_static/noise_dk.png
docs/_static/pygments.css
docs/_static/sphinxdoc.css
docs/_static/fonts/OFLGoudyStMTT-Italic.ttf
docs/_static/fonts/OFLGoudyStMTT.ttf
docs/_static/fonts/YanoneKaffeesatz-Bold.ttf
docs/_static/fonts/YanoneKaffeesatz-Light.ttf
docs/_static/fonts/YanoneKaffeesatz-Regular.ttf
docs/_static/fonts/YanoneKaffeesatz-Thin.ttf
docs/_static/images/arch_layers.png
docs/_static/images/from_&yet.png
docs/api/basexmpp.rst
docs/api/clientxmpp.rst
docs/api/componentxmpp.rst
docs/api/exceptions.rst
docs/api/xmlstream/filesocket.rst
docs/api/xmlstream/handler.rst
docs/api/xmlstream/jid.rst
docs/api/xmlstream/matcher.rst
docs/api/xmlstream/scheduler.rst
docs/api/xmlstream/stanzabase.rst
docs/api/xmlstream/tostring.rst
docs/api/xmlstream/xmlstream.rst
docs/getting_started/component.rst
docs/getting_started/echobot.rst
docs/getting_started/iq.rst
docs/getting_started/muc.rst
docs/getting_started/presence.rst
docs/getting_started/proxy.rst
docs/getting_started/scheduler.rst
docs/getting_started/sendlogout.rst
docs/howto/stanzas.rst
examples/IoT_TestDevice.py
examples/adhoc_provider.py
examples/adhoc_user.py
examples/admin_commands.py
examples/disco_browser.py
examples/download_avatars.py
examples/echo_client.py
examples/echo_component.py
examples/gtalk_custom_domain.py
examples/http_over_xmpp.py
examples/migrate_roster.py
examples/muc.py
examples/ping.py
examples/proxy_echo_client.py
examples/pubsub_client.py
examples/pubsub_events.py
sleekxmpp.egg-info/PKG-INFO
sleekxmpp.egg-info/SOURCES.txt
sleekxmpp.egg-info/dependency_links.txt
sleekxmpp.egg-info/top_level.txt
