Metadata-Version: 1.1
Name: sleekxmpp
Version: 1.3.2
Summary: SleekXMPP is an elegant Python library for XMPP (aka Jabber, Google Talk, etc).
Home-page: http://github.com/fritzy/SleekXMPP
Author: Nathanael Fritz
Author-email: fritzy@netflint.net
License: MIT
Platform: any
Classifier: Intended Audience :: Developers
Classifier: License :: OSI Approved :: MIT License
Classifier: Programming Language :: Python
Classifier: Programming Language :: Python :: 2.6
Classifier: Programming Language :: Python :: 2.7
Classifier: Programming Language :: Python :: 3.1
Classifier: Programming Language :: Python :: 3.2
Classifier: Programming Language :: Python :: 3.3
Classifier: Topic :: Software Development :: Libraries :: Python Modules
Requires: dnspython
Requires: pyasn1
Requires: pyasn1_modules
